CHANGELOG.txt
LICENCE.txt
MANIFEST.in
README.md
README.txt
setup.py
plotclassification/__init__.py
plotclassification.egg-info/PKG-INFO
plotclassification.egg-info/SOURCES.txt
plotclassification.egg-info/dependency_links.txt
plotclassification.egg-info/requires.txt
plotclassification.egg-info/top_level.txt