Metadata-Version: 2.1
Name: plotclassification
Version: 0.0.4
Summary: This package perform different way to visualize machine learning  and deep learning classification results
Home-page: https://github.com/vishalbpatil1/ml_classification_plot
Author: Vishal Patil
Author-email: vishalbpatil1@gmail.com
License: MIT
Keywords: plot classification
Platform: UNKNOWN
Classifier: License :: OSI Approved :: MIT License
Classifier: Programming Language :: Python :: 3
Classifier: Programming Language :: Python :: 3.7
